configs/__init__.py
dd_ranking/__init__.py
dd_ranking/aug/__init__.py
dd_ranking/aug/cutmix.py
dd_ranking/aug/dsa.py
dd_ranking/aug/mixup.py
dd_ranking/aug/zca.py
dd_ranking/config/__init__.py
dd_ranking/config/user_config.py
dd_ranking/loss/__init__.py
dd_ranking/loss/kl.py
dd_ranking/loss/sce.py
dd_ranking/metrics/__init__.py
dd_ranking/metrics/dd_ranking_aug.py
dd_ranking/metrics/general.py
dd_ranking/metrics/hard_label.py
dd_ranking/metrics/soft_label.py
dd_ranking/utils/__init__.py
dd_ranking/utils/data.py
dd_ranking/utils/misc.py
dd_ranking/utils/model.py
dd_ranking/utils/networks.py
dd_ranking/utils/train_and_eval.py
dd_ranking-0.1.1.dist-info/LICENSE
dd_ranking-0.1.1.dist-info/METADATA
dd_ranking-0.1.1.dist-info/WHEEL
dd_ranking-0.1.1.dist-info/top_level.txt
dd_ranking-0.1.1.dist-info/RECORD
