Metadata-Version: 2.1
Name: dd-ranking
Version: 0.1.1
Summary: DD-Ranking: Rethinking the Evaluation of Dataset Distillation
Author: Data Intelligence Team
Author-email: lizekai@u.nus.edu
Classifier: Programming Language :: Python :: 3.8
Classifier: Programming Language :: Python :: 3.9
Classifier: Programming Language :: Python :: 3.10
Classifier: Programming Language :: Python :: 3.11
Classifier: Programming Language :: Python :: 3.12
Classifier: Intended Audience :: Developers
Classifier: Intended Audience :: Information Technology
Classifier: Intended Audience :: Science/Research
Classifier: Topic :: Scientific/Engineering :: Artificial Intelligence
Classifier: Topic :: Scientific/Engineering :: Information Analysis
Classifier: License :: OSI Approved :: MIT License
Classifier: Operating System :: OS Independent
Requires-Python: >=3.8
License-File: LICENSE
Requires-Dist: torch
Requires-Dist: numpy
Requires-Dist: torchvision
Requires-Dist: tqdm
Requires-Dist: scipy
Requires-Dist: kornia
Requires-Dist: timm
